LICENSE
MANIFEST.in
README.rst
gunicorn_console.py
setup.py
gunicorn_console.egg-info/PKG-INFO
gunicorn_console.egg-info/SOURCES.txt
gunicorn_console.egg-info/dependency_links.txt
gunicorn_console.egg-info/entry_points.txt
gunicorn_console.egg-info/requires.txt
gunicorn_console.egg-info/top_level.txt