Metadata-Version: 1.0
Name: gunicorn-console
Version: 0.1.15
Summary: A curses application for managing gunicorn processes.
Home-page: http://github.com/stephenmcd/gunicorn-console/
Author: Stephen McDonald
Author-email: stephen.mc@gmail.com
License: BSD
Platform: UNKNOWN
Classifier: Development Status :: 4 - Beta
Classifier: Environment :: Console :: Curses
Classifier: Intended Audience :: Developers
Classifier: License :: OSI Approved :: BSD License
Classifier: Operating System :: POSIX
Classifier: Programming Language :: Python
Classifier: Topic :: Internet :: WWW/HTTP :: WSGI :: Server
